setup.py
distributions/Binomialdistribution.py
distributions/Gaussiandistribution.py
distributions/Generaldistribution.py
distributions/__init__.py
snddistributions.egg-info/PKG-INFO
snddistributions.egg-info/SOURCES.txt
snddistributions.egg-info/dependency_links.txt
snddistributions.egg-info/not-zip-safe
snddistributions.egg-info/top_level.txt