Metadata-Version: 1.0
Name: snddistributions
Version: 0.1
Summary: Gaussian distributions
Home-page: UNKNOWN
Author: kushagra
Author-email: kushagrarastogiies@gmail.com
License: UNKNOWN
Platform: UNKNOWN
